releasenotes/notes/docker-cmd-paunch-0a674fc1b84b2dfc.yaml
releasenotes/notes/drop-python-2-7-73d3113c69d724d6.yaml
releasenotes/notes/drop-python-3-6-and-3-7-17dd2c0ff96ee806.yaml
releasenotes/notes/heat-config-notify-retry-e01b995d239bb1fd.yaml
releasenotes/notes/hook_docker_envfile-bc9eb287d854e1e1.yaml
releasenotes/notes/remove-py39-2b33de2e95a88bea.yaml
releasenotes/notes/switch-docker-cmd-hook-to-docker-cli-5d8f6deee2125d65.yaml
releasenotes/source/2023.1.rst
releasenotes/source/2023.2.rst
releasenotes/source/2024.1.rst
releasenotes/source/2024.2.rst
releasenotes/source/2025.1.rst
releasenotes/source/conf.py
releasenotes/source/index.rst
releasenotes/source/queens.rst
releasenotes/source/rocky.rst
releasenotes/source/stein.rst
releasenotes/source/train.rst
releasenotes/source/unreleased.rst
releasenotes/source/ussuri.rst
releasenotes/source/victoria.rst
releasenotes/source/wallaby.rst
releasenotes/source/xena.rst
releasenotes/source/yoga.rst
releasenotes/source/zed.rst
heat_agents-11.0.0.dist-info/AUTHORS
heat_agents-11.0.0.dist-info/LICENSE
heat_agents-11.0.0.dist-info/METADATA
heat_agents-11.0.0.dist-info/WHEEL
heat_agents-11.0.0.dist-info/pbr.json
heat_agents-11.0.0.dist-info/top_level.txt
heat_agents-11.0.0.dist-info/RECORD
